{
  "accounts": [
    {
      "account_id": "default_bybit_real_e38dfe54",
      "platform": "bybit",
      "account_type": "real",
      "credentials": {
        "account_id": "3971962",
        "password": "Aq987456!",
        "server": "Bybit-Live-2"
      }
    },
    {
      "account_id": "default_binance_real_fafc20af",
      "platform": "binance",
      "account_type": "real",
      "credentials": {
        "account_id": "5GkClMEFIPLYZ09tMRE76jgsIoo5mEQgBfSGxC4CHGxQQcBf6Ijb6On8QeSfQdvc",
        "password": "ARXkb759WMwx2lnM1DKseS1sDvY65qJUuQ1Y7USlnuw7QIb1BbVUXLNSrssNmrDj"
      }
    }
  ],
  "user_accounts": {
    "default": [
      "default_bybit_real_e38dfe54",
      "default_binance_real_fafc20af"
    ]
  }
}